src/__init__.py
src/__main__.py
src/main.py
src/rag_ar.py
src/rag_en.py
fastapi_test-0.1.0.dist-info/METADATA
fastapi_test-0.1.0.dist-info/WHEEL
fastapi_test-0.1.0.dist-info/entry_points.txt
fastapi_test-0.1.0.dist-info/top_level.txt
fastapi_test-0.1.0.dist-info/RECORD
